mnm4m/__init__.py
mnm4m/add.py
mnm4m-0.1.0.dist-info/METADATA
mnm4m-0.1.0.dist-info/WHEEL
mnm4m-0.1.0.dist-info/entry_points.txt
mnm4m-0.1.0.dist-info/RECORD
